rmtoo/__init__.py
rmtoo/collection/constraints/MinShockResistance.ctr
rmtoo/inputs/RDepConstraints.py
rmtoo/inputs/RDepDependsOn.py
rmtoo/inputs/RDepMasterNodes.py
rmtoo/inputs/RDepNoDirectedCircles.py
rmtoo/inputs/RDepOneComponent.py
rmtoo/inputs/RDepPriority.py
rmtoo/inputs/RDepSolvedBy.py
rmtoo/inputs/ReqCE3.py
rmtoo/inputs/ReqClass.py
rmtoo/inputs/ReqConstraints.py
rmtoo/inputs/ReqDescription.py
rmtoo/inputs/ReqEffortEst.py
rmtoo/inputs/ReqExpectedResult.py
rmtoo/inputs/ReqHistory.py
rmtoo/inputs/ReqInventedBy.py
rmtoo/inputs/ReqInventedOn.py
rmtoo/inputs/ReqName.py
rmtoo/inputs/ReqNote.py
rmtoo/inputs/ReqOwner.py
rmtoo/inputs/ReqPriority.py
rmtoo/inputs/ReqRationale.py
rmtoo/inputs/ReqStatus.py
rmtoo/inputs/ReqTestCase.py
rmtoo/inputs/ReqTopic.py
rmtoo/inputs/ReqType.py
rmtoo/inputs/__init__.py
rmtoo/lib/Analytics.py
rmtoo/lib/BaseRMObject.py
rmtoo/lib/CE3.py
rmtoo/lib/CE3Set.py
rmtoo/lib/ClassType.py
rmtoo/lib/Constraint.py
rmtoo/lib/Constraints.py
rmtoo/lib/CreateMakeDependencies.py
rmtoo/lib/DateUtils.py
rmtoo/lib/Encoding.py
rmtoo/lib/Executor.py
rmtoo/lib/ExecutorTopicContinuum.py
rmtoo/lib/FuncCall.py
rmtoo/lib/GenIterator.py
rmtoo/lib/InputModuleTypes.py
rmtoo/lib/InputModules.py
rmtoo/lib/Markup.py
rmtoo/lib/Output.py
rmtoo/lib/RMTException.py
rmtoo/lib/ReqTagGeneric.py
rmtoo/lib/Requirement.py
rmtoo/lib/RequirementSet.py
rmtoo/lib/RequirementStatus.py
rmtoo/lib/RmtooMain.py
rmtoo/lib/Statistics.py
rmtoo/lib/StdOutputParams.py
rmtoo/lib/StringHelper.py
rmtoo/lib/TestCase.py
rmtoo/lib/TestCases.py
rmtoo/lib/Topic.py
rmtoo/lib/TopicContinuum.py
rmtoo/lib/TopicContinuumSet.py
rmtoo/lib/TopicSet.py
rmtoo/lib/TopicSetWCI.py
rmtoo/lib/UsableFlag.py
rmtoo/lib/__init__.py
rmtoo/lib/analytics/Base.py
rmtoo/lib/analytics/DescWords.py
rmtoo/lib/analytics/HotSpot.py
rmtoo/lib/analytics/ReqTopicCohe.py
rmtoo/lib/analytics/Result.py
rmtoo/lib/analytics/TopicCohe.py
rmtoo/lib/analytics/__init__.py
rmtoo/lib/configuration/Cfg.py
rmtoo/lib/configuration/CfgEx.py
rmtoo-26.0.2.dist-info/licenses/COPYING
rmtoo-26.0.2.dist-info/METADATA
rmtoo-26.0.2.dist-info/WHEEL
rmtoo-26.0.2.dist-info/entry_points.txt
rmtoo-26.0.2.dist-info/top_level.txt
rmtoo-26.0.2.dist-info/RECORD
