Metadata-Version: 2.4
Name: rmtoo
Version: 26.0.2
Summary: Free and OpenSource Requirements Management Tool
Home-page: http://rmtoo.florath.net
Author: Andreas Florath
Author-email: rmtoo@florath.net
License: GPL-3.0-or-later
Keywords: requirements management
Platform: all
Classifier: Development Status :: 6 - Mature
Classifier: Environment :: Console
Classifier: Intended Audience :: Developers
Classifier: Intended Audience :: Education
Classifier: Intended Audience :: End Users/Desktop
Classifier: Intended Audience :: Manufacturing
Classifier: Intended Audience :: Telecommunications Industry
Classifier: Operating System :: MacOS
Classifier: Operating System :: Microsoft :: Windows
Classifier: Operating System :: OS Independent
Classifier: Operating System :: POSIX :: Linux
Classifier: Programming Language :: Python
Classifier: Programming Language :: Python :: 3.8
Classifier: Programming Language :: Python :: 3.9
Classifier: Programming Language :: Python :: 3.10
Classifier: Programming Language :: Python :: 3.11
Classifier: Programming Language :: Python :: 3.12
Classifier: Programming Language :: Python :: 3.13
Classifier: Topic :: Software Development :: Quality Assurance
Classifier: Topic :: Scientific/Engineering
License-File: COPYING
Requires-Dist: numpy>=1.12.0
Requires-Dist: scipy>=0.19.0
Requires-Dist: gitdb>=4.0.1
Requires-Dist: gitpython>=3.1.41
Requires-Dist: pyyaml>=3.12
Requires-Dist: stevedore>=1.21
Requires-Dist: pylint>=1.7.1
Requires-Dist: odfpy==1.3.4
Requires-Dist: jinja2>=2.10
Dynamic: author
Dynamic: author-email
Dynamic: classifier
Dynamic: description
Dynamic: description-content-type
Dynamic: home-page
Dynamic: keywords
Dynamic: license
Dynamic: license-file
Dynamic: platform
Dynamic: requires-dist
Dynamic: summary
